[
  {
    "name": "Afghan Naan-Style Flatbread with Honey",
    "cuisine": "afghan",
    "meal_type": "breakfast",
    "course": "complete",
    "tags": [
      "vegetarian"
    ],
    "base_servings": 1,
    "ingredients": [
      {
        "ingredient": "All-purpose flour",
        "qty": 60,
        "note": ""
      },
      {
        "ingredient": "Yogurt, plain, whole milk",
        "qty": 30,
        "note": ""
      },
      {
        "ingredient": "Baking powder",
        "qty": 0.5,
        "note": "tsp"
      },
      {
        "ingredient": "Honey",
        "qty": 1.5,
        "note": "tbsp"
      }
    ],
    "steps": [
      "Mix the flour, yogurt, and baking powder into a soft dough.",
      "Roll thin and cook on a hot, dry griddle, 2-3 minutes per side, until puffed and speckled.",
      "Drizzle with the honey."
    ],
    "ingredients_full": [
      {
        "ingredient": "All-purpose flour",
        "qty": 70,
        "note": ""
      },
      {
        "ingredient": "Yogurt, plain, whole milk",
        "qty": 35,
        "note": ""
      },
      {
        "ingredient": "Baking powder",
        "qty": 0.75,
        "note": "tsp"
      },
      {
        "ingredient": "Honey",
        "qty": 1.75,
        "note": "tbsp"
      },
      {
        "ingredient": "Butter, salted",
        "qty": 7,
        "note": ""
      }
    ],
    "steps_detailed": [
      "Mix the flour, yogurt, baking powder, and a pinch of salt into a soft, slightly tacky dough, and rest 15-20 minutes.",
      "Roll out thin and cook on a hot, dry griddle, 2-3 minutes per side, until puffed and darkly speckled.",
      "Brush with the butter and drizzle with the honey - naan is central to nearly every meal in Afghanistan, used as much as a utensil as a food itself."
    ]
  },
  {
    "name": "Afghan Eggs with Tomatoes",
    "cuisine": "afghan",
    "meal_type": "breakfast",
    "course": "complete",
    "tags": [
      "vegetarian"
    ],
    "base_servings": 1,
    "ingredients": [
      {
        "ingredient": "Eggs (large)",
        "qty": 2,
        "note": ""
      },
      {
        "ingredient": "Diced tomatoes (canned)",
        "qty": 50,
        "note": ""
      },
      {
        "ingredient": "Yellow onion",
        "qty": 30,
        "note": "chopped"
      },
      {
        "ingredient": "Vegetable oil",
        "qty": 1,
        "note": "tbsp"
      }
    ],
    "steps": [
      "Soften the onion in the oil.",
      "Add the tomatoes and simmer 5 minutes.",
      "Crack in the eggs and cook until set."
    ],
    "ingredients_full": [
      {
        "ingredient": "Eggs (large)",
        "qty": 2.25,
        "note": ""
      },
      {
        "ingredient": "Diced tomatoes (canned)",
        "qty": 60,
        "note": ""
      },
      {
        "ingredient": "Yellow onion",
        "qty": 35,
        "note": "chopped"
      },
      {
        "ingredient": "Vegetable oil",
        "qty": 1.25,
        "note": "tbsp"
      },
      {
        "ingredient": "Garlic clove",
        "qty": 1,
        "note": "minced"
      }
    ],
    "steps_detailed": [
      "Soften the onion and garlic in the oil, 5-6 minutes.",
      "Add the tomatoes and simmer 6-8 minutes until slightly thickened.",
      "Crack in the eggs and cook, covered, 4-5 minutes until the whites are set - a version of this tomato-egg dish is eaten across much of Central and South Asia."
    ]
  },
  {
    "name": "Afghan Oat Porridge",
    "cuisine": "afghan",
    "meal_type": "breakfast",
    "course": "complete",
    "tags": [
      "vegetarian"
    ],
    "base_servings": 1,
    "ingredients": [
      {
        "ingredient": "365 (Whole Foods) Old-Fashioned Rolled Oats",
        "qty": 45,
        "note": ""
      },
      {
        "ingredient": "Whole milk (generic)",
        "qty": 0.75,
        "note": "cup"
      },
      {
        "ingredient": "Honey",
        "qty": 1,
        "note": "tbsp"
      }
    ],
    "steps": [
      "Simmer the oats in the milk for 6-8 minutes, stirring, until thick.",
      "Top with the honey."
    ],
    "ingredients_full": [
      {
        "ingredient": "365 (Whole Foods) Old-Fashioned Rolled Oats",
        "qty": 50,
        "note": ""
      },
      {
        "ingredient": "Whole milk (generic)",
        "qty": 0.9,
        "note": "cup"
      },
      {
        "ingredient": "Honey",
        "qty": 1.25,
        "note": "tbsp"
      },
      {
        "ingredient": "Ground cardamom",
        "qty": 0.0625,
        "note": "tsp"
      }
    ],
    "steps_detailed": [
      "Simmer the oats in the milk and cardamom over medium-low heat, stirring often, 8-10 minutes, until thick and creamy.",
      "Top generously with the honey."
    ]
  },
  {
    "name": "Afghan Kabuli Pulao (Rice with Carrots and Raisins)",
    "cuisine": "afghan",
    "meal_type": "lunch",
    "course": "complete",
    "tags": [],
    "base_servings": 1,
    "ingredients": [
      {
        "ingredient": "Ground lamb",
        "qty": 180,
        "note": "formed into a small roast-style portion"
      },
      {
        "ingredient": "White rice (dry)",
        "qty": 55,
        "note": ""
      },
      {
        "ingredient": "Carrots, baby, raw",
        "qty": 50,
        "note": "julienned"
      },
      {
        "ingredient": "Raisins, dark, seedless (Includes foods for USDA's Food Distribution Program)",
        "qty": 20,
        "note": ""
      }
    ],
    "steps": [
      "Roast the lamb at 375F for 20-22 minutes until browned.",
      "Saute the carrots until softened and lightly caramelized, 8-10 minutes.",
      "Cook the rice, then layer with the carrots and raisins, and serve with the lamb."
    ],
    "ingredients_full": [
      {
        "ingredient": "Ground lamb",
        "qty": 200,
        "note": "formed into a small roast-style portion"
      },
      {
        "ingredient": "White rice (dry)",
        "qty": 60,
        "note": ""
      },
      {
        "ingredient": "Carrots, baby, raw",
        "qty": 60,
        "note": "julienned"
      },
      {
        "ingredient": "Raisins, dark, seedless (Includes foods for USDA's Food Distribution Program)",
        "qty": 25,
        "note": ""
      },
      {
        "ingredient": "Ground cardamom",
        "qty": 0.25,
        "note": "tsp"
      },
      {
        "ingredient": "Nuts, almonds",
        "qty": 10,
        "note": "slivered, to top"
      }
    ],
    "steps_detailed": [
      "Roast the lamb, seasoned with the cardamom, at 375F (190C) for 22-26 minutes until well browned and cooked through.",
      "Saute the carrots until softened and lightly caramelized, 9-11 minutes, with the raisins added in the last 2 minutes to plump.",
      "Cook the rice, layer with the carrot-raisin mixture and slivered almonds, and serve with the lamb.",
      "Kabuli pulao, Afghanistan's national dish, is instantly recognizable by its sweet, jewel-toned topping of caramelized carrot and raisin over rice."
    ]
  },
  {
    "name": "Afghan Mantu-Style Dumplings",
    "cuisine": "afghan",
    "meal_type": "lunch",
    "course": "complete",
    "tags": [],
    "base_servings": 1,
    "ingredients": [
      {
        "ingredient": "All-purpose flour",
        "qty": 55,
        "note": ""
      },
      {
        "ingredient": "Ground beef 90/10",
        "qty": 150,
        "note": ""
      },
      {
        "ingredient": "Yellow onion",
        "qty": 35,
        "note": "finely chopped"
      },
      {
        "ingredient": "Yogurt, plain, whole milk",
        "qty": 40,
        "note": "to top"
      }
    ],
    "steps": [
      "Make a simple dough from the flour and water, roll thin, cut into squares.",
      "Mix the beef and onion, fill the dough, fold and seal, and steam 15-18 minutes.",
      "Top with the yogurt."
    ],
    "ingredients_full": [
      {
        "ingredient": "All-purpose flour",
        "qty": 60,
        "note": ""
      },
      {
        "ingredient": "Ground beef 90/10",
        "qty": 165,
        "note": ""
      },
      {
        "ingredient": "Yellow onion",
        "qty": 40,
        "note": "finely chopped"
      },
      {
        "ingredient": "Yogurt, plain, whole milk",
        "qty": 50,
        "note": "to top"
      },
      {
        "ingredient": "Garlic clove",
        "qty": 1,
        "note": "minced"
      },
      {
        "ingredient": "Spices, turmeric, ground",
        "qty": 0.25,
        "note": ""
      }
    ],
    "steps_detailed": [
      "Make a simple, firm dough from the flour, a pinch of salt, and water, roll thin, and cut into squares.",
      "Mix the beef, onion, garlic, and turmeric, fill the dough, fold and seal well, and steam 16-20 minutes until cooked through.",
      "Top with the yogurt - mantu, steamed dumplings topped with yogurt and often a tomato-based sauce, are a beloved Afghan specialty for special occasions."
    ]
  },
  {
    "name": "Afghan Borani Banjan (Fried Eggplant)",
    "cuisine": "afghan",
    "meal_type": "lunch",
    "course": "complete",
    "tags": [
      "vegetarian"
    ],
    "base_servings": 1,
    "ingredients": [
      {
        "ingredient": "Eggplant, raw",
        "qty": 180,
        "note": "sliced"
      },
      {
        "ingredient": "Yogurt, plain, whole milk",
        "qty": 50,
        "note": ""
      },
      {
        "ingredient": "Diced tomatoes (canned)",
        "qty": 50,
        "note": ""
      },
      {
        "ingredient": "Garlic clove",
        "qty": 1,
        "note": "minced"
      }
    ],
    "steps": [
      "Fry the eggplant slices in oil until golden, about 3-4 minutes per side.",
      "Simmer the tomatoes with the garlic, and pour over the eggplant.",
      "Top with the yogurt."
    ],
    "ingredients_full": [
      {
        "ingredient": "Eggplant, raw",
        "qty": 200,
        "note": "sliced"
      },
      {
        "ingredient": "Yogurt, plain, whole milk",
        "qty": 60,
        "note": ""
      },
      {
        "ingredient": "Diced tomatoes (canned)",
        "qty": 60,
        "note": ""
      },
      {
        "ingredient": "Garlic clove",
        "qty": 1.25,
        "note": "minced"
      },
      {
        "ingredient": "Spices, turmeric, ground",
        "qty": 0.375,
        "note": ""
      },
      {
        "ingredient": "Vegetable oil",
        "qty": 1.5,
        "note": "tbsp, for frying"
      }
    ],
    "steps_detailed": [
      "Fry the eggplant slices in the oil over medium heat, 4-5 minutes per side, until deeply golden and soft.",
      "Simmer the tomatoes with the garlic and turmeric, 8-10 minutes, and pour over the fried eggplant.",
      "Top generously with the yogurt - borani banjan, layered fried eggplant, tomato, and yogurt, is a beloved Afghan side or light meal."
    ]
  },
  {
    "name": "Afghan Lentil Soup",
    "cuisine": "afghan",
    "meal_type": "lunch",
    "course": "complete",
    "tags": [
      "vegetarian",
      "vegan",
      "gluten-free"
    ],
    "base_servings": 1,
    "ingredients": [
      {
        "ingredient": "Lentils, raw",
        "qty": 50,
        "note": ""
      },
      {
        "ingredient": "Yellow onion",
        "qty": 35,
        "note": "chopped"
      },
      {
        "ingredient": "Spices, turmeric, ground",
        "qty": 0.5,
        "note": ""
      },
      {
        "ingredient": "Garlic clove",
        "qty": 1,
        "note": "minced"
      }
    ],
    "steps": [
      "Soften the onion and garlic with the turmeric.",
      "Add the lentils and 2 cups water, and simmer 25-30 minutes until soft."
    ],
    "ingredients_full": [
      {
        "ingredient": "Lentils, raw",
        "qty": 55,
        "note": ""
      },
      {
        "ingredient": "Yellow onion",
        "qty": 40,
        "note": "chopped"
      },
      {
        "ingredient": "Spices, turmeric, ground",
        "qty": 0.625,
        "note": ""
      },
      {
        "ingredient": "Garlic clove",
        "qty": 1.25,
        "note": "minced"
      },
      {
        "ingredient": "Diced tomatoes (canned)",
        "qty": 40,
        "note": ""
      },
      {
        "ingredient": "Ground cumin",
        "qty": 0.5,
        "note": "tsp"
      }
    ],
    "steps_detailed": [
      "Soften the onion, garlic, turmeric, and cumin in a little oil, 5-6 minutes.",
      "Add the lentils, tomatoes, and 2.25 cups water, and simmer 28-32 minutes until soft and thickened."
    ]
  },
  {
    "name": "Afghan Lamb Kebab-Style",
    "cuisine": "afghan",
    "meal_type": "dinner",
    "course": "complete",
    "tags": [],
    "base_servings": 1,
    "ingredients": [
      {
        "ingredient": "Ground lamb",
        "qty": 200,
        "note": "formed into skewer-style portions"
      },
      {
        "ingredient": "Garlic clove",
        "qty": 1.5,
        "note": "minced"
      },
      {
        "ingredient": "Ground cumin",
        "qty": 0.75,
        "note": "tsp"
      },
      {
        "ingredient": "Black pepper (ground)",
        "qty": 0.375,
        "note": "tsp"
      }
    ],
    "steps": [
      "Mix the lamb with the garlic, cumin, and pepper, and shape into small skewer-style portions.",
      "Grill or pan-fry, 8-10 minutes, turning, until cooked through."
    ],
    "ingredients_full": [
      {
        "ingredient": "Ground lamb",
        "qty": 220,
        "note": "formed into skewer-style portions"
      },
      {
        "ingredient": "Garlic clove",
        "qty": 1.75,
        "note": "minced"
      },
      {
        "ingredient": "Ground cumin",
        "qty": 1,
        "note": "tsp"
      },
      {
        "ingredient": "Black pepper (ground)",
        "qty": 0.5,
        "note": "tsp"
      },
      {
        "ingredient": "Spices, coriander seed",
        "qty": 0.5,
        "note": "tsp"
      }
    ],
    "steps_detailed": [
      "Mix the lamb with the garlic, cumin, pepper, and coriander thoroughly, and shape into small, even skewer-style portions.",
      "Grill or pan-fry over medium-high heat, 9-11 minutes, turning, until well browned and cooked through.",
      "Kebab, grilled skewered meat, is the centerpiece of Afghan street food and celebration alike."
    ]
  },
  {
    "name": "Afghan Chicken Curry",
    "cuisine": "afghan",
    "meal_type": "dinner",
    "course": "complete",
    "tags": [],
    "base_servings": 1,
    "ingredients": [
      {
        "ingredient": "Chicken thigh (raw)",
        "qty": 190,
        "note": ""
      },
      {
        "ingredient": "Diced tomatoes (canned)",
        "qty": 70,
        "note": ""
      },
      {
        "ingredient": "Spices, turmeric, ground",
        "qty": 0.5,
        "note": ""
      },
      {
        "ingredient": "Garlic clove",
        "qty": 1.5,
        "note": "minced"
      }
    ],
    "steps": [
      "Brown the chicken with the garlic.",
      "Add the tomatoes and turmeric, and simmer 18-20 minutes until cooked through."
    ],
    "ingredients_full": [
      {
        "ingredient": "Chicken thigh (raw)",
        "qty": 210,
        "note": ""
      },
      {
        "ingredient": "Diced tomatoes (canned)",
        "qty": 80,
        "note": ""
      },
      {
        "ingredient": "Spices, turmeric, ground",
        "qty": 0.625,
        "note": ""
      },
      {
        "ingredient": "Garlic clove",
        "qty": 1.75,
        "note": "minced"
      },
      {
        "ingredient": "Yellow onion",
        "qty": 35,
        "note": "chopped"
      },
      {
        "ingredient": "Ground cumin",
        "qty": 0.5,
        "note": "tsp"
      }
    ],
    "steps_detailed": [
      "Brown the chicken with the onion, garlic, turmeric, and cumin over medium-high heat, 8-10 minutes.",
      "Add the tomatoes and simmer 20-22 minutes until cooked through and thickened."
    ]
  },
  {
    "name": "Afghan Beef and Carrot Stew",
    "cuisine": "afghan",
    "meal_type": "dinner",
    "course": "complete",
    "tags": [],
    "base_servings": 1,
    "ingredients": [
      {
        "ingredient": "Beef, chuck, short ribs, boneless, separable lean and fat, trimmed to 0\" fat, all grades, raw",
        "qty": 190,
        "note": ""
      },
      {
        "ingredient": "Carrots, baby, raw",
        "qty": 90,
        "note": "chunked"
      },
      {
        "ingredient": "Yellow onion",
        "qty": 40,
        "note": "chopped"
      },
      {
        "ingredient": "Ground cumin",
        "qty": 0.5,
        "note": "tsp"
      }
    ],
    "steps": [
      "Brown the beef with the onion and cumin.",
      "Add the carrots and 1.5 cups water, and simmer 35-40 minutes until tender."
    ],
    "ingredients_full": [
      {
        "ingredient": "Beef, chuck, short ribs, boneless, separable lean and fat, trimmed to 0\" fat, all grades, raw",
        "qty": 210,
        "note": ""
      },
      {
        "ingredient": "Carrots, baby, raw",
        "qty": 100,
        "note": "chunked"
      },
      {
        "ingredient": "Yellow onion",
        "qty": 45,
        "note": "chopped"
      },
      {
        "ingredient": "Ground cumin",
        "qty": 0.625,
        "note": "tsp"
      },
      {
        "ingredient": "Garlic clove",
        "qty": 1,
        "note": "minced"
      },
      {
        "ingredient": "Spices, turmeric, ground",
        "qty": 0.375,
        "note": ""
      }
    ],
    "steps_detailed": [
      "Brown the beef with the onion, garlic, cumin, and turmeric over medium-high heat, 9-11 minutes.",
      "Add the carrots and 1.75 cups water, and simmer 38-42 minutes until fully tender."
    ]
  },
  {
    "name": "Afghan Chickpea and Potato Stew",
    "cuisine": "afghan",
    "meal_type": "dinner",
    "course": "complete",
    "tags": [
      "vegetarian",
      "vegan"
    ],
    "base_servings": 1,
    "ingredients": [
      {
        "ingredient": "Chickpeas (garbanzo beans, bengal gram), mature seeds, canned, drained solids",
        "qty": 150,
        "note": ""
      },
      {
        "ingredient": "Yukon gold potato",
        "qty": 100,
        "note": "chunked"
      },
      {
        "ingredient": "Diced tomatoes (canned)",
        "qty": 60,
        "note": ""
      },
      {
        "ingredient": "Spices, turmeric, ground",
        "qty": 0.5,
        "note": ""
      }
    ],
    "steps": [
      "Simmer the chickpeas and potato with the tomatoes and turmeric for 20-22 minutes until tender."
    ],
    "ingredients_full": [
      {
        "ingredient": "Chickpeas (garbanzo beans, bengal gram), mature seeds, canned, drained solids",
        "qty": 170,
        "note": ""
      },
      {
        "ingredient": "Yukon gold potato",
        "qty": 115,
        "note": "chunked"
      },
      {
        "ingredient": "Diced tomatoes (canned)",
        "qty": 70,
        "note": ""
      },
      {
        "ingredient": "Spices, turmeric, ground",
        "qty": 0.625,
        "note": ""
      },
      {
        "ingredient": "Garlic clove",
        "qty": 1,
        "note": "minced"
      },
      {
        "ingredient": "Ground cumin",
        "qty": 0.5,
        "note": "tsp"
      }
    ],
    "steps_detailed": [
      "Simmer the chickpeas, potato, tomatoes, garlic, turmeric, and cumin together over medium-low heat, 22-26 minutes, until the potato is fully tender."
    ]
  },
  {
    "name": "Afghan Yogurt with Honey and Pistachio",
    "cuisine": "afghan",
    "meal_type": "snack",
    "course": "side",
    "tags": [
      "vegetarian",
      "gluten-free"
    ],
    "base_servings": 1,
    "ingredients": [
      {
        "ingredient": "Yogurt, plain, whole milk",
        "qty": 150,
        "note": ""
      },
      {
        "ingredient": "Honey",
        "qty": 1.5,
        "note": "tbsp"
      },
      {
        "ingredient": "Nuts, pistachio nuts, raw",
        "qty": 15,
        "note": "chopped"
      }
    ],
    "steps": [
      "Stir the honey into the yogurt and top with the pistachios."
    ],
    "ingredients_full": [
      {
        "ingredient": "Yogurt, plain, whole milk",
        "qty": 170,
        "note": ""
      },
      {
        "ingredient": "Honey",
        "qty": 1.75,
        "note": "tbsp"
      },
      {
        "ingredient": "Nuts, pistachio nuts, raw",
        "qty": 20,
        "note": "chopped"
      },
      {
        "ingredient": "Ground cardamom",
        "qty": 0.0625,
        "note": "tsp"
      }
    ],
    "steps_detailed": [
      "Stir the honey and cardamom into the yogurt and top with the chopped pistachios."
    ]
  },
  {
    "name": "Afghan Spiced Chickpea Snack",
    "cuisine": "afghan",
    "meal_type": "snack",
    "course": "side",
    "tags": [
      "vegetarian",
      "vegan",
      "gluten-free"
    ],
    "base_servings": 1,
    "ingredients": [
      {
        "ingredient": "Chickpeas (garbanzo beans, bengal gram), mature seeds, canned, drained solids",
        "qty": 120,
        "note": ""
      },
      {
        "ingredient": "Ground cumin",
        "qty": 0.5,
        "note": "tsp"
      },
      {
        "ingredient": "Spices, chili powder",
        "qty": 0.25,
        "note": "tsp"
      },
      {
        "ingredient": "Lime juice",
        "qty": 1,
        "note": "tbsp"
      }
    ],
    "steps": [
      "Toss the chickpeas with the cumin, chili powder, and lime juice."
    ],
    "ingredients_full": [
      {
        "ingredient": "Chickpeas (garbanzo beans, bengal gram), mature seeds, canned, drained solids",
        "qty": 135,
        "note": ""
      },
      {
        "ingredient": "Ground cumin",
        "qty": 0.625,
        "note": "tsp"
      },
      {
        "ingredient": "Spices, chili powder",
        "qty": 0.375,
        "note": "tsp"
      },
      {
        "ingredient": "Lime juice",
        "qty": 1.25,
        "note": "tbsp"
      },
      {
        "ingredient": "Yellow onion",
        "qty": 20,
        "note": "finely chopped"
      }
    ],
    "steps_detailed": [
      "Toss the chickpeas with the cumin, chili powder, lime juice, and onion.",
      "Let sit 10 minutes so the flavors meld."
    ]
  },
  {
    "name": "Afghan Naan with Cheese",
    "cuisine": "afghan",
    "meal_type": "snack",
    "course": "side",
    "tags": [
      "vegetarian"
    ],
    "base_servings": 1,
    "ingredients": [
      {
        "ingredient": "All-purpose flour",
        "qty": 50,
        "note": ""
      },
      {
        "ingredient": "Cheese, feta",
        "qty": 30,
        "note": "crumbled"
      },
      {
        "ingredient": "Yogurt, plain, whole milk",
        "qty": 25,
        "note": ""
      },
      {
        "ingredient": "Baking powder",
        "qty": 0.5,
        "note": "tsp"
      }
    ],
    "steps": [
      "Mix the flour, yogurt, and baking powder into a soft dough.",
      "Roll thin, fill with the cheese, fold, and cook on a hot, dry griddle until golden."
    ],
    "ingredients_full": [
      {
        "ingredient": "All-purpose flour",
        "qty": 55,
        "note": ""
      },
      {
        "ingredient": "Cheese, feta",
        "qty": 35,
        "note": "crumbled"
      },
      {
        "ingredient": "Yogurt, plain, whole milk",
        "qty": 30,
        "note": ""
      },
      {
        "ingredient": "Baking powder",
        "qty": 0.625,
        "note": "tsp"
      },
      {
        "ingredient": "Butter, salted",
        "qty": 7,
        "note": ""
      }
    ],
    "steps_detailed": [
      "Mix the flour, yogurt, baking powder, and a pinch of salt into a soft dough.",
      "Roll thin, fill with the crumbled cheese, fold over, and cook on a hot, dry griddle, 2-3 minutes per side, until golden.",
      "Brush with the butter while warm."
    ]
  },
  {
    "name": "Afghan Pomegranate and Walnut Snack",
    "cuisine": "afghan",
    "meal_type": "snack",
    "course": "side",
    "tags": [
      "vegetarian",
      "vegan",
      "gluten-free",
      "no-cook"
    ],
    "base_servings": 1,
    "ingredients": [
      {
        "ingredient": "Pomegranates, raw",
        "qty": 80,
        "note": "seeds only"
      },
      {
        "ingredient": "Nuts, walnuts, english",
        "qty": 20,
        "note": "chopped"
      },
      {
        "ingredient": "Honey",
        "qty": 1,
        "note": "tbsp"
      }
    ],
    "steps": [
      "Toss the pomegranate seeds with the walnuts and honey."
    ],
    "ingredients_full": [
      {
        "ingredient": "Pomegranates, raw",
        "qty": 90,
        "note": "seeds only"
      },
      {
        "ingredient": "Nuts, walnuts, english",
        "qty": 25,
        "note": "chopped"
      },
      {
        "ingredient": "Honey",
        "qty": 1.25,
        "note": "tbsp"
      },
      {
        "ingredient": "Ground cardamom",
        "qty": 0.0625,
        "note": "tsp"
      }
    ],
    "steps_detailed": [
      "Toss the pomegranate seeds with the walnuts, honey, and a dusting of cardamom - pomegranates are a genuine point of pride in Afghan orchards, especially from the Kandahar region."
    ]
  },
  {
    "name": "Afghan Rice Pudding (Sheer Berenj)",
    "cuisine": "afghan",
    "meal_type": "dessert",
    "course": "complete",
    "tags": [
      "vegetarian",
      "gluten-free"
    ],
    "base_servings": 1,
    "ingredients": [
      {
        "ingredient": "White rice (dry)",
        "qty": 40,
        "note": ""
      },
      {
        "ingredient": "Whole milk (generic)",
        "qty": 0.75,
        "note": "cup"
      },
      {
        "ingredient": "Ground cardamom",
        "qty": 0.125,
        "note": "tsp"
      },
      {
        "ingredient": "Rosewater",
        "qty": 0.25,
        "note": "tsp"
      }
    ],
    "steps": [
      "Simmer the rice in the milk with the cardamom and rosewater for 25-30 minutes until thick and creamy."
    ],
    "ingredients_full": [
      {
        "ingredient": "White rice (dry)",
        "qty": 45,
        "note": ""
      },
      {
        "ingredient": "Whole milk (generic)",
        "qty": 0.9,
        "note": "cup"
      },
      {
        "ingredient": "Ground cardamom",
        "qty": 0.1875,
        "note": "tsp"
      },
      {
        "ingredient": "Rosewater",
        "qty": 0.375,
        "note": "tsp"
      },
      {
        "ingredient": "Nuts, pistachio nuts, raw",
        "qty": 10,
        "note": "chopped, to top"
      }
    ],
    "steps_detailed": [
      "Simmer the rice in the milk with the cardamom and rosewater over low heat, stirring often, 28-32 minutes, until thick and creamy.",
      "Top with the chopped pistachios - sheer berenj, fragrant with rosewater and cardamom, is a beloved Afghan celebration dessert."
    ]
  },
  {
    "name": "Afghan Honey Cake",
    "cuisine": "afghan",
    "meal_type": "dessert",
    "course": "side",
    "tags": [
      "vegetarian"
    ],
    "base_servings": 1,
    "ingredients": [
      {
        "ingredient": "All-purpose flour",
        "qty": 55,
        "note": ""
      },
      {
        "ingredient": "Honey",
        "qty": 2,
        "note": "tbsp"
      },
      {
        "ingredient": "Butter, salted",
        "qty": 15,
        "note": ""
      },
      {
        "ingredient": "Eggs (large)",
        "qty": 1,
        "note": ""
      }
    ],
    "steps": [
      "Cream the butter and honey, beat in the egg, then fold in the flour.",
      "Bake at 350F for 20-22 minutes until a skewer comes out clean."
    ],
    "ingredients_full": [
      {
        "ingredient": "All-purpose flour",
        "qty": 65,
        "note": ""
      },
      {
        "ingredient": "Honey",
        "qty": 2.5,
        "note": "tbsp"
      },
      {
        "ingredient": "Butter, salted",
        "qty": 18,
        "note": ""
      },
      {
        "ingredient": "Eggs (large)",
        "qty": 1.25,
        "note": ""
      },
      {
        "ingredient": "Ground cardamom",
        "qty": 0.125,
        "note": "tsp"
      },
      {
        "ingredient": "Baking powder",
        "qty": 0.5,
        "note": "tsp"
      }
    ],
    "steps_detailed": [
      "Cream the butter and honey together until light, then beat in the egg.",
      "Fold in the flour, cardamom, and baking powder, pour into a small lined pan, and bake at 350F (175C) for 22-26 minutes until a skewer comes out clean."
    ]
  },
  {
    "name": "Afghan Pomegranate and Honey Dessert",
    "cuisine": "afghan",
    "meal_type": "dessert",
    "course": "side",
    "tags": [
      "vegetarian",
      "gluten-free"
    ],
    "base_servings": 1,
    "ingredients": [
      {
        "ingredient": "Pomegranates, raw",
        "qty": 90,
        "note": "seeds only"
      },
      {
        "ingredient": "Honey",
        "qty": 1.5,
        "note": "tbsp"
      },
      {
        "ingredient": "Nuts, pistachio nuts, raw",
        "qty": 15,
        "note": "chopped"
      }
    ],
    "steps": [
      "Toss the pomegranate seeds with the honey and pistachios."
    ],
    "ingredients_full": [
      {
        "ingredient": "Pomegranates, raw",
        "qty": 100,
        "note": "seeds only"
      },
      {
        "ingredient": "Honey",
        "qty": 1.75,
        "note": "tbsp"
      },
      {
        "ingredient": "Nuts, pistachio nuts, raw",
        "qty": 20,
        "note": "chopped"
      },
      {
        "ingredient": "Rosewater",
        "qty": 0.125,
        "note": "tsp"
      }
    ],
    "steps_detailed": [
      "Toss the pomegranate seeds with the honey, pistachios, and a touch of rosewater."
    ]
  },
  {
    "name": "Afghan Yogurt Garlic Sauce",
    "cuisine": "afghan",
    "meal_type": "sauce",
    "course": "side",
    "tags": [
      "vegetarian",
      "gluten-free"
    ],
    "base_servings": 1,
    "ingredients": [
      {
        "ingredient": "Yogurt, plain, whole milk",
        "qty": 100,
        "note": ""
      },
      {
        "ingredient": "Garlic clove",
        "qty": 1,
        "note": "minced"
      },
      {
        "ingredient": "Spearmint, fresh",
        "qty": 1,
        "note": "tbsp, chopped"
      }
    ],
    "steps": [
      "Mix the yogurt, garlic, and mint together."
    ],
    "ingredients_full": [
      {
        "ingredient": "Yogurt, plain, whole milk",
        "qty": 115,
        "note": ""
      },
      {
        "ingredient": "Garlic clove",
        "qty": 1.25,
        "note": "minced"
      },
      {
        "ingredient": "Spearmint, fresh",
        "qty": 1.25,
        "note": "tbsp, chopped"
      },
      {
        "ingredient": "Lime juice",
        "qty": 1,
        "note": "tsp"
      }
    ],
    "steps_detailed": [
      "Mix the yogurt, garlic, mint, and lime juice together into a cool, sharp sauce - served over mantu and countless other Afghan dishes."
    ]
  },
  {
    "name": "Afghan Tomato Cumin Sauce",
    "cuisine": "afghan",
    "meal_type": "sauce",
    "course": "side",
    "tags": [
      "vegetarian",
      "vegan",
      "gluten-free"
    ],
    "base_servings": 1,
    "ingredients": [
      {
        "ingredient": "Diced tomatoes (canned)",
        "qty": 70,
        "note": ""
      },
      {
        "ingredient": "Ground cumin",
        "qty": 0.5,
        "note": "tsp"
      },
      {
        "ingredient": "Garlic clove",
        "qty": 1,
        "note": "minced"
      },
      {
        "ingredient": "Vegetable oil",
        "qty": 1,
        "note": "tbsp"
      }
    ],
    "steps": [
      "Soften the garlic in the oil.",
      "Add the tomatoes and cumin, and simmer 12-15 minutes until thickened."
    ],
    "ingredients_full": [
      {
        "ingredient": "Diced tomatoes (canned)",
        "qty": 80,
        "note": ""
      },
      {
        "ingredient": "Ground cumin",
        "qty": 0.625,
        "note": "tsp"
      },
      {
        "ingredient": "Garlic clove",
        "qty": 1.25,
        "note": "minced"
      },
      {
        "ingredient": "Vegetable oil",
        "qty": 1.25,
        "note": "tbsp"
      },
      {
        "ingredient": "Spices, turmeric, ground",
        "qty": 0.25,
        "note": ""
      }
    ],
    "steps_detailed": [
      "Soften the garlic and turmeric in the oil, 2-3 minutes.",
      "Add the tomatoes and cumin, and simmer 14-16 minutes until thickened - the same tomato base that tops mantu and many other Afghan dishes."
    ]
  }
]